taskimporter/__init__.py
taskimporter/const.py
taskimporter/models/__init__.py
taskimporter/models/service.py
taskimporter/models/task.py
taskimporter/models/task_manager.py
taskimporter/services/__init__.py
taskimporter/services/github_service.py
taskimporter/services/gitlab_service.py
taskimporter/services/jira_service.py
taskimporter/task_managers/__init__.py
taskimporter/task_managers/omnifocus3.py
taskimporter/task_managers/things3.py
taskimporter/taskimporter.py
taskimporter-0.2.2.dist-info/entry_points.txt
taskimporter-0.2.2.dist-info/LICENSES/GPL-3.0-or-later.txt
taskimporter-0.2.2.dist-info/WHEEL
taskimporter-0.2.2.dist-info/METADATA
taskimporter-0.2.2.dist-info/RECORD
