Metadata-Version: 2.1
Name: taskimporter
Version: 0.2.2
Summary: Tool to import tasks from a variety of sources into a task manager
Author: Joshua Mulliken
Author-email: joshua@mulliken.net
Requires-Python: >=3.8,<4.0
Classifier: Programming Language :: Python :: 3
Classifier: Programming Language :: Python :: 3.10
Classifier: Programming Language :: Python :: 3.8
Classifier: Programming Language :: Python :: 3.9
Requires-Dist: Jinja2 (>=3.0.3,<4.0.0)
Requires-Dist: PyGithub (>=1.55,<2.0)
Requires-Dist: appdirs (>=1.4.4,<2.0.0)
Requires-Dist: jira (==3.1.1)
Requires-Dist: python-gitlab (>=3.6.0,<4.0.0)
